{
  "parent": "minecraft:recipes/root",
  "criteria": {
    "has_item0": {
      "trigger": "minecraft:inventory_changed",
      "conditions": {
        "items": [
          {
            "items": [
              "supplementaries:sugar_cube"
            ]
          }
        ]
      }
    },
    "has_the_recipe": {
      "trigger": "minecraft:recipe_unlocked",
      "conditions": {
        "recipe": "supplementaries:/sugar_cube_uncrafting"
      }
    }
  },
  "requirements": [
    [
      "has_item0",
      "has_the_recipe"
    ]
  ],
  "rewards": {
    "recipes": [
      "supplementaries:/sugar_cube_uncrafting"
    ]
  }
}